{"nodes": 6, "crossings": 6, "index": 22, "name": "G6C6I22", "yamada": "-2 + 3*A - 3*A^2 - 2*A^3 + 6*A^4 - 6*A^5 + 2*A^6 + 5*A^7 - 8*A^8 + 8*A^9 - 9*A^10 + 6*A^11 - 3*A^12 - A^13 + 5*A^14 - A^15 - A^16 + 3*A^17 - 3*A^19 + 3*A^20 - 2*A^21", "3D_positions": [{"V0": [52, -40, 0], "V1": [100, 0, 0], "V2": [-22, -39, 0], "V3": [28, -64, 0], "V4": [62, -78, 0], "V5": [-22, -97, 0]}, {"C0+": [62, 78, 20], "C0-": [62, 78, -20], "C1+": [-25, 7, 20], "C1-": [-25, 7, -20], "C2+": [19, -40, 20], "C2-": [19, -40, -20], "C3+": [-22, 97, 20], "C3-": [-22, 97, -20], "C4+": [-90, -43, 20], "C4-": [-90, -43, -20], "C5+": [-90, 43, 20], "C5-": [-90, 43, -20], "0": [62, -14, 0], "1": [33, -1, -10], "2": [42, -54, 0], "3": [90, 43, 10], "4": [90, -43, 0], "5": [24, 28, 0], "6": [22, 97, 0], "7": [10, 84, 0], "8": [-5, -11, -10], "9": [-18, 43, 0], "10": [-46, -25, 0], "11": [10, -27, 10], "12": [-58, -54, 10], "13": [1, -60, -10], "14": [33, -48, 10], "15": [46, -59, 0], "16": [22, -97, 0], "17": [-62, -78, -10], "18": [-62, 78, 0], "19": [-10, 76, 0], "20": [-100, 0, 0]}, [["V1", "0", "V0"], ["V4", "4", "V1"], ["V3", "15", "V4"], ["V5", "17", "C4-", "10", "C1+", "5", "C0-", "6", "C3+", "19", "C5-", "20", "C4+", "12", "V2"], ["V1", "3", "C0+", "7", "C3-", "18", "C5+", "9", "C1-", "8", "V2"], ["V4", "16", "V5"], ["V3", "14", "C2+", "11", "V2"], ["V5", "13", "C2-", "1", "V0"], ["V0", "2", "V3"]]]}