{"nodes": 10, "crossings": 4, "index": 134, "name": "G10C4I134", "yamada": "-2 + 2*A + 2*A^2 - 9*A^3 + 15*A^4 - 5*A^5 - 8*A^6 + 33*A^7 - 43*A^8 + 54*A^9 - 47*A^10 + 38*A^11 - 17*A^12 + 11*A^14 - 9*A^15 + 2*A^16 + 3*A^17 - 3*A^18 + A^19", "3D_positions": [{"V0": [33, 2, 0], "V1": [-5, 42, 0], "V2": [100, 0, 0], "V3": [50, 87, 0], "V4": [-14, -41, 0], "V5": [50, -87, 0], "V6": [-100, 0, 0], "V7": [-50, 87, 0], "V8": [-45, -9, 0], "V9": [-32, -22, 0]}, {"C0+": [-39, 13, 20], "C0-": [-39, 13, -20], "C1+": [-12, -10, 20], "C1-": [-12, -10, -20], "C2+": [-50, -87, 20], "C2-": [-50, -87, -20], "C3+": [-56, -18, 20], "C3-": [-56, -18, -20], "0": [-26, 2, 0], "1": [-17, 23, 10], "2": [-48, 36, -10], "3": [-61, 1, 10], "4": [-9, 13, -10], "5": [-28, -20, -10], "6": [2, -16, 10], "7": [7, 19, 0], "8": [73, 17, 0], "9": [26, 44, 0], "10": [87, 50, 0], "11": [87, -50, 0], "12": [0, 100, 0], "13": [23, -42, 0], "14": [-21, -76, -10], "15": [0, -100, 10], "16": [-87, -50, -10], "17": [-55, -37, 0], "18": [-87, 50, 0], "19": [-75, -9, 10], "20": [-69, -9, -10], "21": [-37, -23, 10], "22": [-35, -17, 0]}, [["V2", "8", "V0"], ["V1", "9", "V3"], ["V3", "12", "V7"], ["V0", "7", "V1"], ["V8", "3", "C0+", "1", "V1"], ["V4", "13", "V5"], ["V6", "18", "V7"], ["V5", "15", "C2+", "17", "C3-", "20", "V8"], ["V9", "5", "C1-", "4", "V0"], ["V3", "10", "V2"], ["V8", "22", "V9"], ["V4", "14", "C2-", "16", "V6"], ["V6", "19", "C3+", "21", "V9"], ["V2", "11", "V5"], ["V4", "6", "C1+", "0", "C0-", "2", "V7"]]]}