{"nodes": 6, "crossings": 6, "index": 124, "name": "G6C6I124", "yamada": "-1 + 2*A^2 - 3*A^3 - 3*A^4 + 7*A^5 - 7*A^6 - 2*A^7 + 8*A^8 - 4*A^9 - 2*A^10 + 9*A^11 - 8*A^12 + 9*A^13 - 8*A^14 + 6*A^15 + 3*A^16 - 12*A^17 + 11*A^18 - 4*A^19 - 5*A^20 + 5*A^21 - A^22 - A^23 + A^24", "3D_positions": [{"V0": [100, 0, 0], "V1": [31, -95, 0], "V2": [54, -20, 0], "V3": [60, -37, 0], "V4": [-47, 3, 0], "V5": [-16, 28, 0]}, {"C0+": [-81, 59, 20], "C0-": [-81, 59, -20], "C1+": [31, 95, 20], "C1-": [31, 95, -20], "C2+": [-81, -59, 20], "C2-": [-81, -59, -20], "C3+": [28, -3, 20], "C3-": [28, -3, -20], "C4+": [19, -35, 20], "C4-": [19, -35, -20], "C5+": [-12, 1, 20], "C5-": [-12, 1, -20], "0": [-31, 95, 0], "1": [-100, 0, 0], "2": [-45, 28, -10], "3": [-22, 61, 0], "4": [81, 59, -10], "5": [36, 30, 0], "6": [81, -59, 0], "7": [76, -12, 0], "8": [-31, -95, 10], "9": [64, -44, 0], "10": [-15, -54, 0], "11": [-52, -27, 10], "12": [73, -17, 0], "13": [61, -8, 10], "14": [41, -47, -10], "15": [0, 9, 0], "16": [34, -19, 0], "17": [2, -16, 0], "18": [-27, -27, -10], "19": [-25, 11, 10], "20": [-36, 20, 0]}, [["V2", "12", "V3"], ["V5", "2", "C0-", "0", "C1+", "5", "C3-", "16", "C4+", "10", "C2-", "1", "C0+", "3", "C1-", "4", "V0"], ["V1", "6", "V0"], ["V4", "18", "C5-", "15", "C3+", "13", "V2"], ["V5", "20", "V4"], ["V4", "11", "C2+", "8", "V1"], ["V0", "7", "V2"], ["V3", "9", "V1"], ["V5", "19", "C5+", "17", "C4-", "14", "V3"]]]}