{"nodes": 14, "crossings": 3, "index": 38, "name": "G14C3I38", "yamada": "-1 + 3*A - A^2 - 15*A^3 + 33*A^4 - 22*A^5 - 53*A^6 + 193*A^7 - 357*A^8 + 496*A^9 - 563*A^10 + 548*A^11 - 445*A^12 + 291*A^13 - 122*A^14 + 3*A^15 + 50*A^16 - 42*A^17 + 19*A^18 - 3*A^19", "3D_positions": [{"V0": [100, 0, 0], "V1": [31, -95, 0], "V2": [-81, -59, 0], "V3": [-81, 59, 0], "V4": [0, -39, 0], "V5": [-26, -12, 0], "V6": [-61, -3, 0], "V7": [34, -11, 0], "V8": [3, -19, 0], "V9": [11, 19, 0], "V10": [-30, 24, 0], "V11": [57, -4, 0], "V12": [78, -2, 0], "V13": [63, -6, 0]}, {"C0+": [31, 95, 20], "C0-": [31, 95, -20], "C1+": [41, -36, 20], "C1-": [41, -36, -20], "C2+": [50, 4, 20], "C2-": [50, 4, -20], "0": [81, 59, -10], "1": [-31, 95, 10], "2": [-17, 49, -10], "3": [48, 29, 0], "4": [81, -59, 0], "5": [85, -1, 0], "6": [-31, -95, 0], "7": [57, -44, 10], "8": [-100, 0, 0], "9": [-17, -64, 0], "10": [-74, -1, 0], "11": [-36, -36, 0], "12": [24, -56, -10], "13": [-56, -25, 0], "14": [-8, -23, 0], "15": [-50, 17, 0], "16": [25, -28, 10], "17": [60, -13, -10], "18": [12, -23, 0], "19": [46, -6, 0], "20": [5, -6, 0], "21": [-15, 10, 0], "22": [32, 4, 10], "23": [47, -4, -10], "24": [71, 0, 10], "25": [51, -7, 0], "26": [77, -3, 0]}, [["V10", "2", "C0-", "0", "V0"], ["V4", "11", "V5"], ["V2", "8", "V3"], ["V11", "19", "V7"], ["V0", "4", "V1"], ["V13", "17", "C1-", "12", "V4"], ["V5", "13", "V6"], ["V3", "1", "C0+", "3", "C2-", "23", "V11"], ["V1", "7", "C1+", "16", "V7"], ["V8", "20", "V9"], ["V10", "21", "V9"], ["V12", "26", "V13"], ["V2", "9", "V4"], ["V0", "5", "V12"], ["V13", "25", "V11"], ["V5", "14", "V8"], ["V3", "10", "V6"], ["V8", "18", "V7"], ["V2", "6", "V1"], ["V10", "15", "V6"], ["V12", "24", "C2+", "22", "V9"]]]}